hired/__init__.py
hired/_converters.py
hired/base.py
hired/config.py
hired/content.py
hired/render.py
hired/resume_agent.py
hired/resumejson_pydantic_models.py
hired/tools.py
hired/util.py
hired/validators.py
hired/renderers/__init__.py
hired/renderers/html.py
hired/renderers/rendercv.py
hired/renderers/w_rendercv.py
hired/search/__init__.py
hired/search/base.py
hired/search/facade.py
hired/search/registry.py
hired/search/sources/__init__.py
hired/search/sources/adzuna.py
hired/search/sources/jobspy.py
hired/search/sources/usajobs.py
hired-0.0.10.dist-info/licenses/LICENSE
hired-0.0.10.dist-info/METADATA
hired-0.0.10.dist-info/WHEEL
hired-0.0.10.dist-info/top_level.txt
hired-0.0.10.dist-info/RECORD
