Metadata-Version: 2.4
Name: hired
Version: 0.0.10
Summary: Streamline the job application process for job seekers - with AI obvs!
Home-page: https://github.com/thorwhalen/hired
Author: Thor Whalen
License: mit
Platform: any
License-File: LICENSE
Requires-Dist: pydantic>=2.0
Requires-Dist: jinja2>=3.0
Requires-Dist: jsonschema>=4.0
Requires-Dist: PyYAML>=6.0
Requires-Dist: requests>=2.28.0
Provides-Extra: testing
Provides-Extra: pdf
Requires-Dist: weasyprint>=58.0; extra == "pdf"
Provides-Extra: rendercv
Requires-Dist: rendercv>=1.2; extra == "rendercv"
Requires-Dist: pyyaml>=6.0; extra == "rendercv"
Provides-Extra: search
Requires-Dist: python-jobspy>=1.1.50; extra == "search"
Provides-Extra: all
Requires-Dist: weasyprint>=58.0; extra == "all"
Requires-Dist: rendercv>=1.2; extra == "all"
Requires-Dist: pyyaml>=6.0; extra == "all"
Requires-Dist: python-jobspy>=1.1.50; extra == "all"
Dynamic: license-file
